{
  "GenusId": "pteropus",
  "SpeciesId": "scapulatus",
  "Name": "Little Red Flying-fox",
  "RegionIds": [
    308,
    307,
    306,
    302,
    304,
    301,
    303,
    304,
    201,
    202,
    102,
    103,
    105,
    106,
    107,
    203
  ],
  "DistributionMapImage": "pteropus_scapulatus_dist.jpg",

"SimilarSpecies": [
    {
      "GenusId": "pteropus",
      "SpeciesId": "alecto"
    },
     {
      "GenusId": "pteropus",
      "SpeciesId": "conspicillatus"
    },
     { 
      "GenusId": "pteropus",
      "SpeciesId": "poliocephalus"
    }
  ]
}